<?xml version="1.0" encoding="UTF-8"?>
<thing:thing-descriptions bindingId="zwave"
  xmlns:xsi="http://www.w3.org/2001/XMLSchema-instance"
  xmlns:thing="http://eclipse.org/smarthome/schemas/thing-description/v1.0.0"
  xsi:schemaLocation="http://eclipse.org/smarthome/schemas/thing-description/v1.0.0
                      http://eclipse.org/smarthome/schemas/thing-description/v1.0.0">

  <thing-type id="willis_zen20_00_000" listed="false">
    <label>ZEN20 Smart Energy Power Strip</label>
    <description><![CDATA[
Smart Energy Power Strip<br /><h2>Inclusion Information</h2><ol><li>Plug the power strip into a grounded receptacle located within direct range from your Z- Wave gateway controller</li> <li>Put your Z-Wave controller in inclusion mode</li> <li>Press and release the CH1 power button on the strip 3 times quickly</li> <li>A new on / off device should appear on your controller's device list</li> </ol><h1>Troubleshooting Tips</h1> <p>If you are unable to include the Z-Wave power strip to your controller, please try one of the following:</p> <ul><li>Bring the power strip closer to your Z-Wave controller</li> <li>Press and release the CH1 power button quickly 7-8 times once you put the controller in the inclusion mode to ensure the command has gone through</li> <li>Put your controller in the EXCLUSION mode and press and release the CH1 power button quickly 3 times, then try adding it to your network again</li> </ul><br /><h2>Exclusion Information</h2><ol><li>Plug the power strip into a grounded receptacle located within direct range from your Z-Wave gateway controller</li> <li>Put your Z-Wave controller in exclusion mode</li> <li>Press and release the CH1 power button on the strip 3 times quickly</li> <li>The device should disappear from your controller's device list</li> </ol><p>Please repeat the process following all steps carefully if the first attempt is unsuccessful</p>
    ]]></description>

    <!-- CHANNEL DEFINITIONS -->
    <channels>
      <channel id="switch_binary1" typeId="switch_binary">
        <label>Switch 1</label>
        <properties>
          <property name="binding:*:OnOffType">COMMAND_CLASS_SWITCH_BINARY:1,COMMAND_CLASS_BASIC:1</property>
        </properties>
      </channel>
      <channel id="switch_binary2" typeId="switch_binary">
        <label>Switch 2</label>
        <properties>
          <property name="binding:*:OnOffType">COMMAND_CLASS_SWITCH_BINARY:2,COMMAND_CLASS_BASIC:2</property>
        </properties>
      </channel>
      <channel id="switch_binary3" typeId="switch_binary">
        <label>Switch 3</label>
        <properties>
          <property name="binding:*:OnOffType">COMMAND_CLASS_SWITCH_BINARY:3,COMMAND_CLASS_BASIC:3</property>
        </properties>
      </channel>
      <channel id="switch_binary4" typeId="switch_binary">
        <label>Switch 4</label>
        <properties>
          <property name="binding:*:OnOffType">COMMAND_CLASS_SWITCH_BINARY:4,COMMAND_CLASS_BASIC:4</property>
        </properties>
      </channel>
      <channel id="switch_binary5" typeId="switch_binary">
        <label>Switch 5</label>
        <properties>
          <property name="binding:*:OnOffType">COMMAND_CLASS_SWITCH_BINARY:5,COMMAND_CLASS_BASIC:5</property>
        </properties>
      </channel>
    </channels>

    <!-- DEVICE PROPERTY DEFINITIONS -->
    <properties>
      <property name="vendor">Willis Electric Co., Ltd.</property>
      <property name="modelId">ZEN20</property>
      <property name="manufacturerId">015D</property>
      <property name="manufacturerRef">0651:F51C</property>
      <property name="dbReference">541</property>
    </properties>

    <!-- CONFIGURATION DESCRIPTIONS -->
    <config-description>

      <!-- STATIC DEFINITIONS -->
      <parameter name="node_id" type="integer" min="1" max="232" readOnly="true" required="true">
        <label>Node ID</label>
      </parameter>

    </config-description>

  </thing-type>

</thing:thing-descriptions>
